avocado/__init__.py
avocado/__main__.py
avocado/core/__init__.py
avocado/core/app.py
avocado/core/data_dir.py
avocado/core/decorators.py
avocado/core/dispatcher.py
avocado/core/enabled_extension_manager.py
avocado/core/exceptions.py
avocado/core/exit_codes.py
avocado/core/extension_manager.py
avocado/core/job.py
avocado/core/job_id.py
avocado/core/jobdata.py
avocado/core/main.py
avocado/core/messages.py
avocado/core/output.py
avocado/core/parameters.py
avocado/core/parser.py
avocado/core/parser_common_args.py
avocado/core/plugin_interfaces.py
avocado/core/references.py
avocado/core/resolver.py
avocado/core/result.py
avocado/core/settings.py
avocado/core/settings_dispatcher.py
avocado/core/streams.py
avocado/core/suite.py
avocado/core/sysinfo.py
avocado/core/tags.py
avocado/core/tapparser.py
avocado/core/test.py
avocado/core/test_id.py
avocado/core/teststatus.py
avocado/core/tree.py
avocado/core/varianter.py
avocado/core/version.py
avocado/core/dependencies/__init__.py
avocado/core/dependencies/dependency.py
avocado/core/dependencies/requirements/__init__.py
avocado/core/dependencies/requirements/cache/__init__.py
avocado/core/dependencies/requirements/cache/backends/__init__.py
avocado/core/dependencies/requirements/cache/backends/sqlite.py
avocado/core/nrunner/__init__.py
avocado/core/nrunner/app.py
avocado/core/nrunner/config.py
avocado/core/nrunner/runnable.py
avocado/core/nrunner/runner.py
avocado/core/nrunner/task.py
avocado/core/safeloader/__init__.py
avocado/core/safeloader/core.py
avocado/core/safeloader/docstring.py
avocado/core/safeloader/imported.py
avocado/core/safeloader/module.py
avocado/core/safeloader/utils.py
avocado/core/spawners/__init__.py
avocado/core/spawners/common.py
avocado/core/spawners/exceptions.py
avocado/core/spawners/mock.py
avocado/core/status/__init__.py
avocado/core/status/repo.py
avocado/core/status/server.py
avocado/core/status/utils.py
avocado/core/task/__init__.py
avocado/core/task/runtime.py
avocado/core/task/statemachine.py
avocado_framework-113.0.dist-info/licenses/LICENSE
avocado_framework-113.0.dist-info/METADATA
avocado_framework-113.0.dist-info/WHEEL
avocado_framework-113.0.dist-info/entry_points.txt
avocado_framework-113.0.dist-info/top_level.txt
avocado_framework-113.0.dist-info/RECORD
